{"sections":{"locator_i_GFCqyt":{"type":"locator-i","name":"Locator I","settings":{"heading":"FIND JUSTNOSH NEAR YOU","stockist_widget_tag":"map_r3mn7jvq","load_stockist_script":true}},"main":{"type":"locator-ii","settings":{"heading":"DON'T SEE JUSTNOSH AT A STORE NEAR YOU?","subheading":"Let us know where you shop, or reach out about carrying JustNosh.\nWe read every message.","button_label":"CONTACT US","email_note":"<p>Or email us directly at <a href=\"mailto:hello@jagprovisions.com\" target=\"_blank\" title=\"mailto:hello@jagprovisions.com\">hello@jagprovisions.com<\/a><\/p>"}}},"order":["locator_i_GFCqyt","main"]}